vecscan/__init__.py
vecscan/scanner.py
vecscan/utils.py
vecscan/vector_loader/__init__.py
vecscan/vector_loader/__main__.py
vecscan/vectorizer/__init__.py
vecscan/vectorizer/__main__.py
vecscan-2.1.0.dist-info/LICENSE
vecscan-2.1.0.dist-info/METADATA
vecscan-2.1.0.dist-info/WHEEL
vecscan-2.1.0.dist-info/entry_points.txt
vecscan-2.1.0.dist-info/top_level.txt
vecscan-2.1.0.dist-info/RECORD
