Metadata-Version: 2.1
Name: vecscan
Version: 2.1.0
Summary: vecscan: A Linear-scan-based High-speed Dense Vector Search Engine
Home-page: https://github.com/megagonlabs/vecscan
Author: Megagon Labs, Tokyo.
Author-email: vecscan@megagon.ai
License: MIT
Platform: UNKNOWN
Requires-Python: >=3.8
License-File: LICENSE
Requires-Dist: torch >=2.0.1
Requires-Dist: numpy
Requires-Dist: safetensors >=0.3.1
Requires-Dist: tqdm
